machine_learning_datasets/__init__.py
machine_learning_datasets/common.py
machine_learning_datasets/config.py
machine_learning_datasets/container.py
machine_learning_datasets/deprecated.py
machine_learning_datasets/dsconfig.json
machine_learning_datasets/evaluate.py
machine_learning_datasets/interpret.py
machine_learning_datasets/preprocess.py
machine_learning_datasets/sources/__init__.py
machine_learning_datasets/sources/kaggle.py
machine_learning_datasets/sources/source.py
machine_learning_datasets/sources/url.py
machine_learning_datasets-0.1.23.dist-info/LICENSE
machine_learning_datasets-0.1.23.dist-info/METADATA
machine_learning_datasets-0.1.23.dist-info/WHEEL
machine_learning_datasets-0.1.23.dist-info/RECORD
